nidmd/__init__.py
nidmd/core/__init__.py
nidmd/core/decomposition.py
nidmd/core/timeseries.py
nidmd/datasets/__init__.py
nidmd/datasets/atlas.py
nidmd/datasets/data/ATLAS.JSON
nidmd/datasets/data/glasser.json
nidmd/datasets/data/schaefer.json
nidmd/plotting/__init__.py
nidmd/plotting/brain.py
nidmd/plotting/colors.py
nidmd/plotting/radar.py
nidmd/plotting/spectre.py
nidmd/plotting/timeplot.py
nidmd/tests/__init__.py
nidmd/tests/test_core.py
nidmd-0.2.4.dist-info/LICENSE
nidmd-0.2.4.dist-info/METADATA
nidmd-0.2.4.dist-info/WHEEL
nidmd-0.2.4.dist-info/top_level.txt
nidmd-0.2.4.dist-info/RECORD
