Metadata-Version: 2.1
Name: nidmd
Version: 0.2.4
Summary: Dynamic Mode Decomposition of time-series fMRI
Home-page: https://github.com/arnauddhaene/nidmd
Author: Arnaud Dhaene (EPFL)
Author-email: arnaud.dhaene@epfl.ch
License: UNKNOWN
Platform: UNKNOWN
Classifier: Programming Language :: Python :: 3
Classifier: License :: OSI Approved :: MIT License
Classifier: Operating System :: OS Independent
Requires-Dist: statsmodels
Requires-Dist: pandas
Requires-Dist: numpy
Requires-Dist: plotly
Requires-Dist: nilearn
Requires-Dist: matplotlib
Requires-Dist: scikit-learn
Requires-Dist: scipy
Requires-Dist: sklearn
